bytez/__init__.py
bytez/client.py
bytez/interface.py
bytez/main.py
bytez/main_dep.py
bytez/model.py
bytez-2.0.4.dist-info/METADATA
bytez-2.0.4.dist-info/WHEEL
bytez-2.0.4.dist-info/top_level.txt
bytez-2.0.4.dist-info/RECORD
