Metadata-Version: 2.1
Name: bytez
Version: 2.0.4
Summary: Python API client for Bytez service
Home-page: https://github.com/bytez-com/docs
Author: Bytez
License: UNKNOWN
Platform: UNKNOWN
Classifier: Development Status :: 4 - Beta
Classifier: Intended Audience :: Developers
Classifier: License :: OSI Approved :: MIT License
Classifier: Programming Language :: Python :: 3
Classifier: Programming Language :: Python :: 3.8
Requires-Dist: requests (>=2.32.1)
